mux4t1.v
`timescale 1ns / 1ps
//////////////////////////////////////////////////////////////////////////////////
// Author: Ritav
//
// Create Date: 08.04.2026 13:42:20
// Design Name: 1-bit 4:1 Multiplexer
// Module Name: mux4t1
// Target Devices: Simulation Only
// Tool Versions: Vivado 2025.2
// Description: 
//     4:1 Mux (mux4t1) using 2:1 Mux (mux2t1), structural representation, enable port.
// Dependencies: 
//     mux4t1.v, mux2t1.v
// Revision:
//     Revision 0.01 - File Created
//     Revision 0.02 - fixed unknown behaviour encountered during simulation (at enable=0, any input undefined)

// Additional Comments:
// I[0]-I[2] as mux-1 inputs, I[1]-I[3] as mux-2 inputs. This order is chosen so that: sel=00 -> I[0], sel=01 -> I[1], sel=10 -> I[2], sel=11 -> I[3].
// When Enable is 0, Output is: X when any input is undefined, 0 when all inputs are defined
//////////////////////////////////////////////////////////////////////////////////

//-----------------------------------------------
//1-bit 4:1 MUX using 2:1 MUX- Structural representation
module mux4t1(in, en, sel, dout);
input en; //enable
input [3:0]in; //4 input lines
input [1:0]sel; //2 select lines
output dout; //output data

//net(s)
wire I1_I3, I2_I4; //outputs of first stage 2:1 mux

//three 2:1 mux are used to model 4:1 mux
mux2t1 MuxI0_I2(.in1(in[0]), .in2(in[2]), .en(en), .sel(sel[0]), .dout(I1_I3)); //first stage mux
mux2t1 MuxI1_I3(.in1(in[1]), .in2(in[3]), .en(en), .sel(sel[0]), .dout(I2_I4)); //first stage mux
mux2t1 MuxI13_I24(.in1(I1_I3), .in2(I2_I4), .en(en), .sel(sel[1]), .dout(dout)); //second stage mux

endmodule
//------------------------------------------------
//2:1 MUX - Structural representation
module mux2t1(in1, in2, en, sel, dout);
input en; //enable
input sel; //select line
input in1; //first data input, I1
input in2; //second data input, I2
output dout; //output

//net(s)
wire bsel; //sel_inverted
wire I1_selected, I2_selected; //Ix is selected
wire I1_enabled, I2_enabled; //enable Ix_selected
wire mdout; //output of mux logic
wire sel_x; //'X' if select line is X, otherwise 0
wire in1_x; //'X' if input_1 is 'X', otherwise 0
wire in2_x; //'X' if input_2 is 'X', otherwise 0
wire any_x; //if any input is 'X', any_x is 'X' otherwise 0
wire force_x; //if enable is low and any input is 'X', force_x= 'X', otherwise 0

//structural representation of 2:1 mux
not SelBar(bsel, sel); 
and(I2_selected, bsel, in1);
and(I1_selected, sel, in2); 
and(I1_enabled, en, I1_selected);
and(I2_enabled, en, I2_selected); 
or(mdout, I1_enabled, I2_enabled); 

//when en=0, sel=x, in=x, dout=0 instead of 'X'; here's the fix
xor z(sel_x, sel, sel); //sel_x always 0 when sel is defined, otherwise 'X'
xor x(in1_x, in1, in1); //similar behaviour as sel_x 
xor c(in2_x, in2, in2); //similar behaviour as sel_x
not a(b_en, en);
or b(any_x, sel_x, in1_x, in2_x);
and m(force_x, b_en, any_x); //
or d(dout, force_x, mdout); //if force_x is 'X', output data line is 'X'

endmodule
//------------------------------------------------

tb_mux4t1.v
`timescale 1ns / 1ps
//////////////////////////////////////////////////////////////////////////////////
// Author: Ritik
//
// Create Date: 08.04.2026 13:42:40
// Design Name: 1-bit 4:1 MUX testbench
// Module Name: tb_mux4t1
// Project Name: MUX Implementation
// Target Devices: Simulation Only
// Tool Versions: Vivado 2025.2
// Description: 
//     Testbench for 1-bit 4:1 multiplexer (mux4t1), verifies functionality with all input combinations and enable states.
// Dependencies: 
//     Modules: mux4t1, mux2t1
// Revision:
//     Revision 0.01 - File Created
// Additional Comments:
//     Simulation includes undefined inputs to test X-propagation and enable behavior.
//////////////////////////////////////////////////////////////////////////////////

module tb_mux4t1();
reg en;
reg [3:0]in;
reg [1:0]sel;
wire dout;

//instantiation
mux4t1 MUX(.en(en), .in(in), .sel(sel), .dout(dout));

initial begin //enable signal for all 2:1 mux
#2 en = 1'b0;
#13 en = 1'b1;
end

//select signal, sel[0] for both of first stage 2:1 mux, sel[1] for second stage 2:1 mux
initial repeat(5) begin 
#5 sel = 2'b00;
#5 sel = 2'b01;
#5 sel = 2'b10;
#5 sel = 2'b11;
end

initial begin //input lines, in[0] in[1] in[2] in[3], for 4:1 mux
#5 in = 4'bx;
#5 in = 4'b0;
#5 in = 4'b1;
#5 in = 4'b10;
#5 in = 4'b0011;
#5 in = 4'b0100;
#5 in = 4'b0101;
#5 in = 4'b0110;
#5 in = 4'b0111;
#5 in = 4'b1000;
#5 in = 4'b1001;
#5 in = 4'b1010;
#5 in = 4'b1011;
#5 in = 4'b1100;
#5 in = 4'b1101;
#5 in = 4'b1110;
#5 in = 4'b1111;
#5 $finish; //time = 90
end

initial begin //capture
$monitor("At time: ", $time, ", EN: %b, Sel: %b, Inputs: %b and Dout: %b", en, sel, in, dout, "\nAt first stage 2t1 mux between, I1_I3: %b, I2_I4: %b", mux4t1.I1_I3, mux4t1.I2_I4);
$dumpfile("mux4t1.vcd"); 
$dumpvars(0, tb_mux4t1);
end

endmodule

mux4t1.vcd
$date
   Thu Apr  9 17:11:26 2026
$end

$version
  2025.2
  $dumpfile ("mux4t1.vcd") 
$end

$timescale
  1ps
$end

$scope module tb_mux4t1 $end
$var reg 1 ! en $end
$var reg 4 " in [3:0] $end
$var reg 2 # sel [1:0] $end
$var wire 1 $ dout $end
$scope module MUX $end
$var wire 1 % en $end
$var wire 4 & in [3:0] $end
$var wire 2 ' sel [1:0] $end
$var wire 1 $ dout $end
$var wire 1 ( I1_I3 $end
$var wire 1 ) I2_I4 $end
$scope module MuxI0_I2 $end
$var wire 1 % en $end
$var wire 1 * sel $end
$var wire 1 + in1 $end
$var wire 1 , in2 $end
$var wire 1 ( dout $end
$var wire 1 - bsel $end
$var wire 1 . I1_selected $end
$var wire 1 / I2_selected $end
$var wire 1 0 I1_enabled $end
$var wire 1 1 I2_enabled $end
$var wire 1 2 mdout $end
$var wire 1 3 sel_x $end
$var wire 1 4 in1_x $end
$var wire 1 5 in2_x $end
$var wire 1 6 any_x $end
$var wire 1 7 force_x $end
$var wire 1 8 b_en $end
$upscope $end
$scope module MuxI1_I3 $end
$var wire 1 % en $end
$var wire 1 * sel $end
$var wire 1 9 in1 $end
$var wire 1 : in2 $end
$var wire 1 ) dout $end
$var wire 1 ; bsel $end
$var wire 1 < I1_selected $end
$var wire 1 = I2_selected $end
$var wire 1 > I1_enabled $end
$var wire 1 ? I2_enabled $end
$var wire 1 @ mdout $end
$var wire 1 A sel_x $end
$var wire 1 B in1_x $end
$var wire 1 C in2_x $end
$var wire 1 D any_x $end
$var wire 1 E force_x $end
$var wire 1 F b_en $end
$upscope $end
$scope module MuxI13_I24 $end
$var wire 1 % en $end
$var wire 1 G sel $end
$var wire 1 ( in1 $end
$var wire 1 ) in2 $end
$var wire 1 $ dout $end
$var wire 1 H bsel $end
$var wire 1 I I1_selected $end
$var wire 1 J I2_selected $end
$var wire 1 K I1_enabled $end
$var wire 1 L I2_enabled $end
$var wire 1 M mdout $end
$var wire 1 N sel_x $end
$var wire 1 O in1_x $end
$var wire 1 P in2_x $end
$var wire 1 Q any_x $end
$var wire 1 R force_x $end
$var wire 1 S b_en $end
$upscope $end
$upscope $end
$upscope $end
$enddefinitions $end

#0
$dumpvars
x!
bx "
bx #
x$
x%
bx &
bx '
x(
x)
x*
x+
x,
x-
x.
x/
x0
x1
x2
x3
x4
x5
x6
x7
x8
x9
x:
x;
x<
x=
x>
x?
x@
xA
xB
xC
xD
xE
xF
xG
xH
xI
xJ
xK
xL
xM
xN
xO
xP
xQ
xR
xS
$end

#2000
0!
0%
00
01
02
18
0>
0?
0@
1F
0K
0L
0M
1S

#5000
b0 #
b0 '
0*
1-
0.
03
1;
0<
0A
0G
1H
0I
0N

#10000
b0 "
b1 #
0$
b0 &
b1 '
0(
0)
1*
0+
0,
0-
0/
04
05
06
07
09
0:
0;
0=
0B
0C
0D
0E
0G
0J
0O
0P
0Q
0R

#15000
1!
b1 "
b10 #
1%
b1 &
b10 '
1(
0*
1+
0,
1-
1/
11
12
08
09
0:
1;
0F
1G
0H
0S

#20000
b10 "
b11 #
b10 &
b11 '
0(
1*
0+
0,
0-
0/
01
02
19
0:
0;
1G

#25000
b11 "
b0 #
1$
b11 &
b0 '
1(
1)
0*
1+
0,
1-
1/
11
12
19
0:
1;
1=
1?
1@
0G
1H
1J
1L
1M

#30000
b100 "
b1 #
b100 &
b1 '
0)
1*
0+
1,
0-
1.
0/
10
01
09
0:
0;
0=
0?
0@
0G

#35000
b101 "
b10 #
0$
b101 &
b10 '
0*
1+
1,
1-
0.
1/
00
11
09
0:
1;
1G
0H
0J
0L
0M

#40000
b110 "
b11 #
b110 &
b11 '
1*
0+
1,
0-
1.
0/
10
01
19
0:
0;
1G

#45000
b111 "
b0 #
1$
b111 &
b0 '
1)
0*
1+
1,
1-
0.
1/
00
11
19
0:
1;
1=
1?
1@
0G
1H
1J
1L
1M

#50000
b1000 "
b1 #
0$
b1000 &
b1 '
0(
1*
0+
0,
0-
0/
01
02
09
1:
0;
1<
0=
1>
0?
0G
0J
0L
0M

#55000
b1001 "
b10 #
0$
b1001 &
b10 '
1(
0)
0*
1+
0,
1-
1/
11
12
09
1:
1;
0<
0>
0@
1G
0H
0I
0K
0M

#60000
b1010 "
b11 #
1$
b1010 &
b11 '
0(
1)
1*
0+
0,
0-
0/
01
02
19
1:
0;
1<
1>
1@
1G
1I
1K
1M

#65000
b1011 "
b0 #
1$
b1011 &
b0 '
1(
0*
1+
0,
1-
1/
11
12
19
1:
1;
0<
1=
0>
1?
0G
1H
0I
1J
0K
1L
1M

#70000
b1100 "
b1 #
b1100 &
b1 '
1*
0+
1,
0-
1.
0/
10
01
09
1:
0;
1<
0=
1>
0?
0G

#75000
b1101 "
b10 #
0$
b1101 &
b10 '
0)
0*
1+
1,
1-
0.
1/
00
11
09
1:
1;
0<
0>
0@
1G
0H
0I
0J
0K
0L
0M

#80000
b1110 "
b11 #
1$
b1110 &
b11 '
1)
1*
0+
1,
0-
1.
0/
10
01
19
1:
0;
1<
1>
1@
1G
1I
1K
1M

#85000
b1111 "
b0 #
b1111 &
b0 '
0*
1+
1,
1-
0.
1/
00
11
19
1:
1;
0<
1=
0>
1?
0G
1H
0I
1J
0K
1L
